PyDebugTool/__init__.py
PyDebugTool/debug.py
PyDebugTools-0.2.1.dist-info/METADATA
PyDebugTools-0.2.1.dist-info/WHEEL
PyDebugTools-0.2.1.dist-info/entry_points.txt
PyDebugTools-0.2.1.dist-info/top_level.txt
PyDebugTools-0.2.1.dist-info/RECORD
