Metadata-Version: 2.1
Name: PyDebugTools
Version: 0.2.1
Summary: A Python library for debugging python files and notebooks using GROQ
Home-page: https://github.com/SAMBITMALLICK2003/PyDebugTools
Author: Sambit Mallick
Author-email: sambitmallick.pro@gmail.com
License: MIT
Classifier: Programming Language :: Python :: 3
Classifier: License :: OSI Approved :: MIT License
Classifier: Operating System :: OS Independent
Requires-Python: >=3.6
Requires-Dist: ipython
Requires-Dist: rich
Requires-Dist: langchain-groq
